wigle/cmd.py
wigle/__init__.py
wigle-0.0.4.dist-info/DESCRIPTION.rst
wigle-0.0.4.dist-info/entry_points.txt
wigle-0.0.4.dist-info/METADATA
wigle-0.0.4.dist-info/top_level.txt
wigle-0.0.4.dist-info/RECORD
wigle-0.0.4.dist-info/WHEEL
wigle-0.0.4.dist-info/metadata.json
