Metadata-Version: 2.0
Name: wigle
Version: 0.0.4
Summary: Interface to wigle website
Home-page: https://github.com/viraptor/wigle
Author: Stanisław Pitucha
Author-email: viraptor@gmail.com
License: MIT
Keywords: wigle wifi api search
Platform: UNKNOWN
Classifier: Development Status :: 4 - Beta
Classifier: Intended Audience :: Developers
Classifier: License :: OSI Approved :: MIT License
Classifier: Programming Language :: Python :: 3
Classifier: Topic :: Software Development :: Libraries
Classifier: Topic :: System :: Networking
Classifier: Topic :: Utilities
Requires-Dist: requests
